{
  "schema_version": "rk-v1-starter-seed",
  "source_doc": "docs/design/v1-starter-data-tables.md",
  "source_section": "Civilization Flavor Unit Modifiers (`units.unit_variant_modifiers`)",
  "table_id": "units.unit_variant_modifiers",
  "rows": [
    {
      "variant_unit_id": "brand_levies",
      "modifier_key": "cost_total",
      "operation": "mult",
      "value": 0.9,
      "condition": "always"
    },
    {
      "variant_unit_id": "brand_levies",
      "modifier_key": "train_time_s",
      "operation": "mult",
      "value": 0.85,
      "condition": "always"
    },
    {
      "variant_unit_id": "brand_levies",
      "modifier_key": "attack",
      "operation": "mult",
      "value": 0.88,
      "condition": "always"
    },
    {
      "variant_unit_id": "brand_levies",
      "modifier_key": "def_vs_infantry",
      "operation": "mult",
      "value": 1.08,
      "condition": "always"
    },
    {
      "variant_unit_id": "brand_levies",
      "modifier_key": "hp",
      "operation": "mult",
      "value": 1.05,
      "condition": "stationed_at_home_settlement=true"
    },
    {
      "variant_unit_id": "tribunal_crossmen",
      "modifier_key": "attack",
      "operation": "mult",
      "value": 1.08,
      "condition": "always"
    },
    {
      "variant_unit_id": "tribunal_crossmen",
      "modifier_key": "vision_tiles",
      "operation": "add",
      "value": 1,
      "condition": "stationed_at_home_settlement=true"
    },
    {
      "variant_unit_id": "tribunal_crossmen",
      "modifier_key": "def_vs_ranged",
      "operation": "mult",
      "value": 1.1,
      "condition": "stationed_at_home_settlement=true"
    },
    {
      "variant_unit_id": "ash_riders",
      "modifier_key": "speed_tiles_per_h",
      "operation": "mult",
      "value": 0.95,
      "condition": "always"
    },
    {
      "variant_unit_id": "ash_riders",
      "modifier_key": "def_vs_cavalry",
      "operation": "mult",
      "value": 1.15,
      "condition": "always"
    },
    {
      "variant_unit_id": "ash_riders",
      "modifier_key": "attack",
      "operation": "mult",
      "value": 0.95,
      "condition": "target_is_settlement=false"
    },
    {
      "variant_unit_id": "ember_rams",
      "modifier_key": "train_time_s",
      "operation": "mult",
      "value": 0.9,
      "condition": "always"
    },
    {
      "variant_unit_id": "ember_rams",
      "modifier_key": "structure_damage",
      "operation": "mult",
      "value": 1.05,
      "condition": "always"
    },
    {
      "variant_unit_id": "reed_stalkers",
      "modifier_key": "speed_tiles_per_h",
      "operation": "mult",
      "value": 1.1,
      "condition": "always"
    },
    {
      "variant_unit_id": "reed_stalkers",
      "modifier_key": "vision_tiles",
      "operation": "add",
      "value": 1,
      "condition": "always"
    },
    {
      "variant_unit_id": "reed_stalkers",
      "modifier_key": "retreat_escape_chance",
      "operation": "add",
      "value": 0.12,
      "condition": "always"
    },
    {
      "variant_unit_id": "bog_spearmen",
      "modifier_key": "cost_total",
      "operation": "mult",
      "value": 0.92,
      "condition": "always"
    },
    {
      "variant_unit_id": "bog_spearmen",
      "modifier_key": "def_vs_cavalry",
      "operation": "mult",
      "value": 1.18,
      "condition": "always"
    },
    {
      "variant_unit_id": "bog_spearmen",
      "modifier_key": "hp",
      "operation": "mult",
      "value": 0.92,
      "condition": "always"
    },
    {
      "variant_unit_id": "rot_slingers",
      "modifier_key": "attack",
      "operation": "mult",
      "value": 0.92,
      "condition": "always"
    },
    {
      "variant_unit_id": "rot_slingers",
      "modifier_key": "combat_postfight_attrition_duration_s",
      "operation": "add",
      "value": 300,
      "condition": "hit_confirmed=true"
    },
    {
      "variant_unit_id": "mire_hounds",
      "modifier_key": "speed_tiles_per_h",
      "operation": "mult",
      "value": 1.12,
      "condition": "always"
    },
    {
      "variant_unit_id": "mire_hounds",
      "modifier_key": "carry",
      "operation": "mult",
      "value": 0.75,
      "condition": "always"
    },
    {
      "variant_unit_id": "mire_hounds",
      "modifier_key": "attack",
      "operation": "mult",
      "value": 1.05,
      "condition": "target_retreating=true"
    },
    {
      "variant_unit_id": "pit_guard",
      "modifier_key": "hp",
      "operation": "mult",
      "value": 1.22,
      "condition": "always"
    },
    {
      "variant_unit_id": "pit_guard",
      "modifier_key": "attack",
      "operation": "mult",
      "value": 1.1,
      "condition": "always"
    },
    {
      "variant_unit_id": "pit_guard",
      "modifier_key": "speed_tiles_per_h",
      "operation": "mult",
      "value": 0.82,
      "condition": "always"
    },
    {
      "variant_unit_id": "pit_guard",
      "modifier_key": "train_time_s",
      "operation": "mult",
      "value": 1.2,
      "condition": "always"
    },
    {
      "variant_unit_id": "chainthrowers",
      "modifier_key": "attack",
      "operation": "mult",
      "value": 1.12,
      "condition": "always"
    },
    {
      "variant_unit_id": "chainthrowers",
      "modifier_key": "def_vs_infantry",
      "operation": "mult",
      "value": 1.08,
      "condition": "always"
    },
    {
      "variant_unit_id": "chainthrowers",
      "modifier_key": "speed_tiles_per_h",
      "operation": "mult",
      "value": 0.9,
      "condition": "always"
    },
    {
      "variant_unit_id": "tithe_boars",
      "modifier_key": "attack",
      "operation": "mult",
      "value": 1.18,
      "condition": "always"
    },
    {
      "variant_unit_id": "tithe_boars",
      "modifier_key": "speed_tiles_per_h",
      "operation": "mult",
      "value": 0.88,
      "condition": "always"
    },
    {
      "variant_unit_id": "tithe_boars",
      "modifier_key": "post_combat_recovery_time_s",
      "operation": "add",
      "value": 120,
      "condition": "charge_committed=true"
    },
    {
      "variant_unit_id": "woe_trebuchet",
      "modifier_key": "structure_damage",
      "operation": "mult",
      "value": 1.25,
      "condition": "always"
    },
    {
      "variant_unit_id": "woe_trebuchet",
      "modifier_key": "train_time_s",
      "operation": "mult",
      "value": 1.3,
      "condition": "always"
    },
    {
      "variant_unit_id": "woe_trebuchet",
      "modifier_key": "speed_tiles_per_h",
      "operation": "mult",
      "value": 0.75,
      "condition": "always"
    }
  ]
}
